odoo/addons/privacy_partner_report/README.rst
odoo/addons/privacy_partner_report/__init__.py
odoo/addons/privacy_partner_report/__manifest__.py
odoo/addons/privacy_partner_report/i18n/de.po
odoo/addons/privacy_partner_report/i18n/it.po
odoo/addons/privacy_partner_report/i18n/privacy_partner_report.pot
odoo/addons/privacy_partner_report/readme/CONTRIBUTORS.rst
odoo/addons/privacy_partner_report/readme/DESCRIPTION.rst
odoo/addons/privacy_partner_report/readme/USAGE.rst
odoo/addons/privacy_partner_report/report/__init__.py
odoo/addons/privacy_partner_report/report/privacy_partner_xlsx.py
odoo/addons/privacy_partner_report/static/description/icon.png
odoo/addons/privacy_partner_report/static/description/index.html
odoo/addons/privacy_partner_report/views/privacy_menu_view.xml
odoo/addons/privacy_partner_report/views/privacy_report.xml
odoo/addons/privacy_partner_report/wizard/__init__.py
odoo/addons/privacy_partner_report/wizard/privacy_report_partner.py
odoo/addons/privacy_partner_report/wizard/privacy_report_partner_wizard.xml
odoo11_addon_privacy_partner_report-11.0.1.0.0.99.dev10.dist-info/METADATA
odoo11_addon_privacy_partner_report-11.0.1.0.0.99.dev10.dist-info/WHEEL
odoo11_addon_privacy_partner_report-11.0.1.0.0.99.dev10.dist-info/top_level.txt
odoo11_addon_privacy_partner_report-11.0.1.0.0.99.dev10.dist-info/RECORD
